erome/__init__.py
erome/constants.py
erome/erome.py
drome-1.0.0.dist-info/LICENSE
drome-1.0.0.dist-info/METADATA
drome-1.0.0.dist-info/WHEEL
drome-1.0.0.dist-info/entry_points.txt
drome-1.0.0.dist-info/top_level.txt
drome-1.0.0.dist-info/RECORD
