Metadata-Version: 2.1
Name: drome
Version: 1.0.0
Summary: A program for downloading photos and videos from EroMe
Home-page: https://github.com/santamation/EroMe
Author: santamation
Author-email: santaautomation@protonmail.com
License: UNKNOWN
Keywords: erome,scraper,download,photos,videos
Platform: UNKNOWN
Classifier: Development Status :: 5 - Production/Stable
Classifier: Programming Language :: Python :: 3.6
Classifier: Programming Language :: Python :: 3.7
Classifier: Programming Language :: Python :: 3.8
Classifier: Programming Language :: Python :: 3.9
Classifier: License :: OSI Approved :: GNU General Public License v3 or later (GPLv3+)
Classifier: Operating System :: OS Independent
License-File: LICENSE
Requires-Dist: requests
Requires-Dist: beautifulsoup4
Requires-Dist: lxml
Requires-Dist: tqdm
Requires-Dist: halo
